wah/__init__.py
wah/config.py
wah/data.py
wah/log.py
wah/metrics.py
wah/train.py
wah/typing.py
wah/utils.py
wah-0.1.10.dist-info/LICENSE
wah-0.1.10.dist-info/METADATA
wah-0.1.10.dist-info/WHEEL
wah-0.1.10.dist-info/top_level.txt
wah-0.1.10.dist-info/RECORD
